stonkgs/__init__.py
stonkgs/__main__.py
stonkgs/cli.py
stonkgs/constants.py
stonkgs/version.py
stonkgs/api/__init__.py
stonkgs/api/api.py
stonkgs/api/example.py
stonkgs/api/get_emmaa.py
stonkgs/api/reach_output.json
stonkgs/data/__init__.py
stonkgs/data/filter_evidences.py
stonkgs/data/filter_for_majority_classes.py
stonkgs/data/fix_broken_pretraining_dataset.py
stonkgs/data/indra_check_overlaps.py
stonkgs/data/indra_extraction.py
stonkgs/data/indra_for_pretraining.py
stonkgs/models/__init__.py
stonkgs/models/kg_baseline_model.py
stonkgs/models/nlp_baseline_model.py
stonkgs/models/node2vec.py
stonkgs/models/stonkgs_finetuning.py
stonkgs/models/stonkgs_for_embeddings.py
stonkgs/models/stonkgs_model.py
stonkgs/models/stonkgs_pretraining.py
stonkgs-0.1.5.dist-info/LICENSE
stonkgs-0.1.5.dist-info/METADATA
stonkgs-0.1.5.dist-info/WHEEL
stonkgs-0.1.5.dist-info/entry_points.txt
stonkgs-0.1.5.dist-info/top_level.txt
stonkgs-0.1.5.dist-info/RECORD
