Metadata-Version: 2.1
Name: stonkgs
Version: 0.1.5
Summary: Sophisticated Transformers for Biomedical Text and Knowledge Graph Data
Home-page: https://github.com/stonkgs/stonkgs
Author: helena balabin
Author-email: helena.balabin@scai.fraunhofer.de
Maintainer: helena balabin
Maintainer-email: helena.balabin@scai.fraunhofer.de
License: MIT
Download-URL: https://github.com/stonkgs/stonkgs/releases
Project-URL: Bug Tracker, https://github.com/stonkgs/stonkgs/issues
Project-URL: Source Code, https://github.com/stonkgs/stonkgs
Keywords: natural language processing,transformers,knowledge graphs,representation learning,deep learning,machine learning,bioinformatics
Platform: UNKNOWN
Classifier: Development Status :: 1 - Planning
Classifier: Environment :: Console
Classifier: Intended Audience :: Developers
Classifier: License :: OSI Approved :: MIT License
Classifier: Operating System :: OS Independent
Classifier: Framework :: Pytest
Classifier: Framework :: tox
Classifier: Framework :: Sphinx
Classifier: Programming Language :: Python
Classifier: Programming Language :: Python :: 3.7
Classifier: Programming Language :: Python :: 3.8
Classifier: Programming Language :: Python :: 3 :: Only
Classifier: Topic :: Scientific/Engineering :: Artificial Intelligence
Classifier: Topic :: Scientific/Engineering :: Bio-Informatics
Classifier: Topic :: Text Processing
Requires-Python: <3.9.0,>=3.6.0
License-File: LICENSE
Requires-Dist: more-itertools
Requires-Dist: ijson
Requires-Dist: jupyterlab
Requires-Dist: ipywidgets
Requires-Dist: tqdm
Requires-Dist: click
Requires-Dist: more-click
Requires-Dist: python-dotenv
Requires-Dist: accelerate
Requires-Dist: pytorch-lightning
Requires-Dist: numpy
Requires-Dist: pandas
Requires-Dist: matplotlib
Requires-Dist: seaborn
Requires-Dist: scikit-learn
Requires-Dist: torch (==1.8.1)
Requires-Dist: transformers (==4.6.1)
Requires-Dist: datasets (==1.6.2)
Requires-Dist: tokenizers
Requires-Dist: mlflow
Requires-Dist: optuna
Requires-Dist: psutil
Requires-Dist: indra
Requires-Dist: stellargraph
Requires-Dist: nodevectors
Requires-Dist: pybel
Requires-Dist: pystow
Provides-Extra: docs
Requires-Dist: sphinx ; extra == 'docs'
Requires-Dist: sphinx-rtd-theme ; extra == 'docs'
Requires-Dist: sphinx-click ; extra == 'docs'
Requires-Dist: sphinx-autodoc-typehints ; extra == 'docs'
Requires-Dist: sphinx-automodapi ; extra == 'docs'
Requires-Dist: texext ; extra == 'docs'
